{
	"pages": [ //pages数组中第一项表示应用启动页，参考：https://uniapp.dcloud.io/collocation/pages
		{
			"path": "pages/index/index",
			"style": {
				"navigationBarTitleText": "智能家居控制台"
			}
		},
		{
			"path" : "pages/configPage/configPage",
			"style" : 
			{
				"navigationBarTitleText" : ""
			}
		}
	],
	"globalStyle": {
		"navigationBarTextStyle": "black",
		"navigationBarTitleText": "智能家居控制台",
		"navigationBarBackgroundColor": "#F8F8F8",
		"backgroundColor": "#F8F8F8"
	},
	"uniIdRouter": {},
	
	"tabBar": {
	    "selectedColor": "#6d6d6d",
	    "color": "#ccc",
	    "list": [{
	        "text": "首页",
	        "pagePath": "pages/index/index",
	        "iconPath": "../../static/home2.png",
	        "selectedIconPath": "../../static/home.png"
	      },
	      {
	        "text": "阈值控制",
	        "pagePath": "pages/configPage/configPage",
	        "iconPath": "../../static/config2.png",
	        "selectedIconPath": "../../static/config1.png"
	      }
	    ]
	  }

}
